howdyho/__init__.py
howdyho/__main__.py
howdyho-3.0.1.dist-info/entry_points.txt
howdyho-3.0.1.dist-info/LICENSE
howdyho-3.0.1.dist-info/WHEEL
howdyho-3.0.1.dist-info/METADATA
howdyho-3.0.1.dist-info/RECORD
